director/__init__.py
pal3thorn_director-3.1.4.data/scripts/tasker
pal3thorn_director-3.1.4.dist-info/LICENSE
pal3thorn_director-3.1.4.dist-info/METADATA
pal3thorn_director-3.1.4.dist-info/WHEEL
pal3thorn_director-3.1.4.dist-info/top_level.txt
pal3thorn_director-3.1.4.dist-info/RECORD
