Metadata-Version: 2.2
Name: pal3thorn-director
Version: 3.1.4
Summary: Module for automated remote management
Home-page: https://github.com/Palethorn/director
Author: David Cavar
Author-email: wizzard405@gmail.com
Classifier: Programming Language :: Python :: 3
Classifier: License :: OSI Approved :: MIT License
Classifier: Operating System :: OS Independent
Requires-Python: >=3.6
License-File: LICENSE
Requires-Dist: pyyaml
Requires-Dist: colorama
Requires-Dist: jinja2
Dynamic: author
Dynamic: author-email
Dynamic: classifier
Dynamic: description-content-type
Dynamic: home-page
Dynamic: requires-dist
Dynamic: requires-python
Dynamic: summary
